LICENSE
MANIFEST.in
README.md
setup.py
articleinfo/__init__.py
articleinfo/articleInfo.py
articleinfo.egg-info/PKG-INFO
articleinfo.egg-info/SOURCES.txt
articleinfo.egg-info/dependency_links.txt
articleinfo.egg-info/top_level.txt
articleinfo/getArticleInfoFromCitation/__init__.py
articleinfo/getArticleInfoFromCitation/apa.py
articleinfo/getArticleInfoFromCitation/getArticleInfoFromCitationController.py
articleinfo/getArticleInfoFromCitation/gettableArticleInfo.py
articleinfo/tests/__init__.py
articleinfo/tests/test_all.py
articleinfo/tests/test_apa.py
scripts/articleinfo