Metadata-Version: 1.1
Name: articleinfo
Version: 1.0.1
Summary: Get article information from your entered citation text.
Home-page: https://github.com/YutoMizutani/articleinfo
Author: Yuto Mizutani
Author-email: yuto.mizutani.dev@gmail.com
License: MIT License
